Metadata-Version: 2.1
Name: crypted-cookie-monster
Version: 0.9.0
Summary: ccm - A python library that helps to identify vulnerabilities when processing encrypted data.
Home-page: https://github.com/qtc-de/crypted-cookie-monster
Author: Tobias Neitzel (@qtc_de)
Author-email: 
License: UNKNOWN
Platform: UNKNOWN
Classifier: Programming Language :: Python :: 3
Classifier: Operating System :: Unix
Classifier: License :: OSI Approved :: GNU General Public License v3 (GPLv3)
